[
  {
    "pk_unique_id": "636",
    "facility_name": "Shai-Osudoku District Hospital",
    "facility_type": "hospital",
    "region": "Greater Accra",
    "city": "Dodowa",
    "claimed_specialty": "Ophthalmology",
    "specialty_key": "ophthalmology",
    "has_equipment": "True",
    "has_capability": "True",
    "has_procedure": "True",
    "reason": "Ophthalmology requires eye examination equipment",
    "severity": "HIGH",
    "flag_type": "MEDICAL_INCONSISTENCY"
  },
  {
    "pk_unique_id": "636",
    "facility_name": "Shai-Osudoku District Hospital",
    "facility_type": "hospital",
    "region": "Greater Accra",
    "city": "Dodowa",
    "claimed_specialty": "Pediatrics",
    "specialty_key": "pediatrics",
    "has_equipment": "True",
    "has_capability": "True",
    "has_procedure": "True",
    "reason": "Pediatrics requires child-specific care facilities",
    "severity": "HIGH",
    "flag_type": "MEDICAL_INCONSISTENCY"
  },
  {
    "pk_unique_id": "636",
    "facility_name": "Shai-Osudoku District Hospital",
    "facility_type": "hospital",
    "region": "Greater Accra",
    "city": "Dodowa",
    "claimed_specialty": "Pathology / Laboratory",
    "specialty_key": "pathology",
    "has_equipment": "True",
    "has_capability": "True",
    "has_procedure": "True",
    "reason": "Pathology requires laboratory facilities",
    "severity": "HIGH",
    "flag_type": "MEDICAL_INCONSISTENCY"
  },
  {
    "pk_unique_id": "432",
    "facility_name": "MAB International Hospital",
    "facility_type": "hospital",
    "region": "Greater Accra",
    "city": "Darkuman-Nyamekye",
    "claimed_specialty": "Ophthalmology",
    "specialty_key": "ophthalmology",
    "has_equipment": "True",
    "has_capability": "True",
    "has_procedure": "True",
    "reason": "Ophthalmology requires eye examination equipment",
    "severity": "HIGH",
    "flag_type": "MEDICAL_INCONSISTENCY"
  },
  {
    "pk_unique_id": "673",
    "facility_name": "St. Francis Xavier Hospital",
    "facility_type": "hospital",
    "region": "Central",
    "city": "Assin-Foso",
    "claimed_specialty": "Gynecology & Obstetrics",
    "specialty_key": "gynecologyAndObstetrics",
    "has_equipment": "False",
    "has_capability": "True",
    "has_procedure": "False",
    "reason": "OB/GYN requires maternity/delivery facilities",
    "severity": "HIGH",
    "flag_type": "MEDICAL_INCONSISTENCY"
  },
  {
    "pk_unique_id": "673",
    "facility_name": "St. Francis Xavier Hospital",
    "facility_type": "hospital",
    "region": "Central",
    "city": "Assin-Foso",
    "claimed_specialty": "Pediatrics",
    "specialty_key": "pediatrics",
    "has_equipment": "False",
    "has_capability": "True",
    "has_procedure": "False",
    "reason": "Pediatrics requires child-specific care facilities",
    "severity": "HIGH",
    "flag_type": "MEDICAL_INCONSISTENCY"
  },
  {
    "pk_unique_id": "514",
    "facility_name": "Nyaho Medical Centre",
    "facility_type": "clinic",
    "region": "Unknown",
    "city": "Accra",
    "claimed_specialty": "Cardiology",
    "specialty_key": "cardiology",
    "has_equipment": "False",
    "has_capability": "True",
    "has_procedure": "True",
    "reason": "Cardiology requires cardiac diagnostic equipment (ECG/echo)",
    "severity": "HIGH",
    "flag_type": "MEDICAL_INCONSISTENCY"
  },
  {
    "pk_unique_id": "514",
    "facility_name": "Nyaho Medical Centre",
    "facility_type": "clinic",
    "region": "Unknown",
    "city": "Accra",
    "claimed_specialty": "Pediatrics",
    "specialty_key": "pediatrics",
    "has_equipment": "False",
    "has_capability": "True",
    "has_procedure": "True",
    "reason": "Pediatrics requires child-specific care facilities",
    "severity": "HIGH",
    "flag_type": "MEDICAL_INCONSISTENCY"
  },
  {
    "pk_unique_id": "382",
    "facility_name": "Kings and Queens Medical University Teaching Hospital",
    "facility_type": "hospital",
    "region": "Eastern",
    "city": "Akosombo",
    "claimed_specialty": "General Surgery",
    "specialty_key": "generalSurgery",
    "has_equipment": "False",
    "has_capability": "True",
    "has_procedure": "False",
    "reason": "Surgery requires an operating theatre and surgical equipment",
    "severity": "HIGH",
    "flag_type": "MEDICAL_INCONSISTENCY"
  },
  {
    "pk_unique_id": "382",
    "facility_name": "Kings and Queens Medical University Teaching Hospital",
    "facility_type": "hospital",
    "region": "Eastern",
    "city": "Akosombo",
    "claimed_specialty": "Cardiology",
    "specialty_key": "cardiology",
    "has_equipment": "False",
    "has_capability": "True",
    "has_procedure": "False",
    "reason": "Cardiology requires cardiac diagnostic equipment (ECG/echo)",
    "severity": "HIGH",
    "flag_type": "MEDICAL_INCONSISTENCY"
  },
  {
    "pk_unique_id": "382",
    "facility_name": "Kings and Queens Medical University Teaching Hospital",
    "facility_type": "hospital",
    "region": "Eastern",
    "city": "Akosombo",
    "claimed_specialty": "Radiology",
    "specialty_key": "radiology",
    "has_equipment": "False",
    "has_capability": "True",
    "has_procedure": "False",
    "reason": "Radiology requires imaging equipment",
    "severity": "HIGH",
    "flag_type": "MEDICAL_INCONSISTENCY"
  },
  {
    "pk_unique_id": "382",
    "facility_name": "Kings and Queens Medical University Teaching Hospital",
    "facility_type": "hospital",
    "region": "Eastern",
    "city": "Akosombo",
    "claimed_specialty": "Nephrology",
    "specialty_key": "nephrology",
    "has_equipment": "False",
    "has_capability": "True",
    "has_procedure": "False",
    "reason": "Nephrology requires dialysis or renal care facilities",
    "severity": "HIGH",
    "flag_type": "MEDICAL_INCONSISTENCY"
  },
  {
    "pk_unique_id": "382",
    "facility_name": "Kings and Queens Medical University Teaching Hospital",
    "facility_type": "hospital",
    "region": "Eastern",
    "city": "Akosombo",
    "claimed_specialty": "Emergency Medicine",
    "specialty_key": "emergencyMedicine",
    "has_equipment": "False",
    "has_capability": "True",
    "has_procedure": "False",
    "reason": "Emergency medicine requires 24/7 emergency unit or ambulance",
    "severity": "HIGH",
    "flag_type": "MEDICAL_INCONSISTENCY"
  },
  {
    "pk_unique_id": "382",
    "facility_name": "Kings and Queens Medical University Teaching Hospital",
    "facility_type": "hospital",
    "region": "Eastern",
    "city": "Akosombo",
    "claimed_specialty": "Critical Care / ICU",
    "specialty_key": "criticalCareMedicine",
    "has_equipment": "False",
    "has_capability": "True",
    "has_procedure": "False",
    "reason": "Critical care requires ICU / intensive care unit",
    "severity": "HIGH",
    "flag_type": "MEDICAL_INCONSISTENCY"
  },
  {
    "pk_unique_id": "382",
    "facility_name": "Kings and Queens Medical University Teaching Hospital",
    "facility_type": "hospital",
    "region": "Eastern",
    "city": "Akosombo",
    "claimed_specialty": "Neurosurgery",
    "specialty_key": "neurosurgery",
    "has_equipment": "False",
    "has_capability": "True",
    "has_procedure": "False",
    "reason": "Neurosurgery requires surgical facilities and neurosurgical equipment",
    "severity": "HIGH",
    "flag_type": "MEDICAL_INCONSISTENCY"
  },
  {
    "pk_unique_id": "382",
    "facility_name": "Kings and Queens Medical University Teaching Hospital",
    "facility_type": "hospital",
    "region": "Eastern",
    "city": "Akosombo",
    "claimed_specialty": "Cardiac Surgery",
    "specialty_key": "cardiacSurgery",
    "has_equipment": "False",
    "has_capability": "True",
    "has_procedure": "False",
    "reason": "Cardiac surgery requires operating theatre and cardiac support",
    "severity": "HIGH",
    "flag_type": "MEDICAL_INCONSISTENCY"
  },
  {
    "pk_unique_id": "382",
    "facility_name": "Kings and Queens Medical University Teaching Hospital",
    "facility_type": "hospital",
    "region": "Eastern",
    "city": "Akosombo",
    "claimed_specialty": "Infectious Diseases (incl. TB)",
    "specialty_key": "infectiousDiseases",
    "has_equipment": "False",
    "has_capability": "True",
    "has_procedure": "False",
    "reason": "Infectious disease care requires lab/testing or isolation facilities",
    "severity": "HIGH",
    "flag_type": "MEDICAL_INCONSISTENCY"
  },
  {
    "pk_unique_id": "382",
    "facility_name": "Kings and Queens Medical University Teaching Hospital",
    "facility_type": "hospital",
    "region": "Eastern",
    "city": "Akosombo",
    "claimed_specialty": "Gynecology & Obstetrics",
    "specialty_key": "gynecologyAndObstetrics",
    "has_equipment": "False",
    "has_capability": "True",
    "has_procedure": "False",
    "reason": "OB/GYN requires maternity/delivery facilities",
    "severity": "HIGH",
    "flag_type": "MEDICAL_INCONSISTENCY"
  },
  {
    "pk_unique_id": "382",
    "facility_name": "Kings and Queens Medical University Teaching Hospital",
    "facility_type": "hospital",
    "region": "Eastern",
    "city": "Akosombo",
    "claimed_specialty": "Pediatrics",
    "specialty_key": "pediatrics",
    "has_equipment": "False",
    "has_capability": "True",
    "has_procedure": "False",
    "reason": "Pediatrics requires child-specific care facilities",
    "severity": "HIGH",
    "flag_type": "MEDICAL_INCONSISTENCY"
  },
  {
    "pk_unique_id": "382",
    "facility_name": "Kings and Queens Medical University Teaching Hospital",
    "facility_type": "hospital",
    "region": "Eastern",
    "city": "Akosombo",
    "claimed_specialty": "Pathology / Laboratory",
    "specialty_key": "pathology",
    "has_equipment": "False",
    "has_capability": "True",
    "has_procedure": "False",
    "reason": "Pathology requires laboratory facilities",
    "severity": "HIGH",
    "flag_type": "MEDICAL_INCONSISTENCY"
  },
  {
    "pk_unique_id": "405",
    "facility_name": "Kwadwo Boapim Herbal Clinic",
    "facility_type": "clinic",
    "region": "Unknown",
    "city": "Accra",
    "claimed_specialty": "Cardiology",
    "specialty_key": "cardiology",
    "has_equipment": "False",
    "has_capability": "True",
    "has_procedure": "False",
    "reason": "Cardiology requires cardiac diagnostic equipment (ECG/echo)",
    "severity": "HIGH",
    "flag_type": "MEDICAL_INCONSISTENCY"
  },
  {
    "pk_unique_id": "405",
    "facility_name": "Kwadwo Boapim Herbal Clinic",
    "facility_type": "clinic",
    "region": "Unknown",
    "city": "Accra",
    "claimed_specialty": "Gynecology & Obstetrics",
    "specialty_key": "gynecologyAndObstetrics",
    "has_equipment": "False",
    "has_capability": "True",
    "has_procedure": "False",
    "reason": "OB/GYN requires maternity/delivery facilities",
    "severity": "HIGH",
    "flag_type": "MEDICAL_INCONSISTENCY"
  },
  {
    "pk_unique_id": "184",
    "facility_name": "Danpong HealthCare",
    "facility_type": "clinic",
    "region": "Unknown",
    "city": "Accra",
    "claimed_specialty": "Ophthalmology",
    "specialty_key": "ophthalmology",
    "has_equipment": "True",
    "has_capability": "True",
    "has_procedure": "True",
    "reason": "Ophthalmology requires eye examination equipment",
    "severity": "HIGH",
    "flag_type": "MEDICAL_INCONSISTENCY"
  },
  {
    "pk_unique_id": "459",
    "facility_name": "Medicas Hospital, Mampong-Akuapem",
    "facility_type": "hospital",
    "region": "Unknown",
    "city": "Akuapem Mampong",
    "claimed_specialty": "Gynecology & Obstetrics",
    "specialty_key": "gynecologyAndObstetrics",
    "has_equipment": "True",
    "has_capability": "True",
    "has_procedure": "True",
    "reason": "OB/GYN requires maternity/delivery facilities",
    "severity": "HIGH",
    "flag_type": "MEDICAL_INCONSISTENCY"
  },
  {
    "pk_unique_id": "251",
    "facility_name": "Finney Hospital and Fertility Centre",
    "facility_type": "hospital",
    "region": "Unknown",
    "city": "Accra",
    "claimed_specialty": "Gynecology & Obstetrics",
    "specialty_key": "gynecologyAndObstetrics",
    "has_equipment": "False",
    "has_capability": "True",
    "has_procedure": "False",
    "reason": "OB/GYN requires maternity/delivery facilities",
    "severity": "HIGH",
    "flag_type": "MEDICAL_INCONSISTENCY"
  },
  {
    "pk_unique_id": "665",
    "facility_name": "St. Andrew Catholic Hospital, Kordiabe",
    "facility_type": "hospital",
    "region": "Greater Accra",
    "city": "Kordiabe",
    "claimed_specialty": "Gynecology & Obstetrics",
    "specialty_key": "gynecologyAndObstetrics",
    "has_equipment": "True",
    "has_capability": "True",
    "has_procedure": "False",
    "reason": "OB/GYN requires maternity/delivery facilities",
    "severity": "HIGH",
    "flag_type": "MEDICAL_INCONSISTENCY"
  },
  {
    "pk_unique_id": "1",
    "facility_name": "West Africa AIDS Foundation",
    "facility_type": "nan",
    "region": "Unknown",
    "city": "Haatso",
    "claimed_specialty": "Infectious Diseases (incl. TB)",
    "specialty_key": "infectiousDiseases",
    "has_equipment": "False",
    "has_capability": "False",
    "has_procedure": "False",
    "reason": "Infectious disease care requires lab/testing or isolation facilities",
    "severity": "MEDIUM",
    "flag_type": "MEDICAL_INCONSISTENCY"
  },
  {
    "pk_unique_id": "483",
    "facility_name": "Mission Clinic",
    "facility_type": "clinic",
    "region": "Greater Accra",
    "city": "Accra",
    "claimed_specialty": "Ophthalmology",
    "specialty_key": "ophthalmology",
    "has_equipment": "False",
    "has_capability": "True",
    "has_procedure": "False",
    "reason": "Ophthalmology requires eye examination equipment",
    "severity": "HIGH",
    "flag_type": "MEDICAL_INCONSISTENCY"
  },
  {
    "pk_unique_id": "729",
    "facility_name": "The Community Hospital New Ashongman",
    "facility_type": "hospital",
    "region": "Unknown",
    "city": "New Ashongman",
    "claimed_specialty": "Gynecology & Obstetrics",
    "specialty_key": "gynecologyAndObstetrics",
    "has_equipment": "False",
    "has_capability": "True",
    "has_procedure": "False",
    "reason": "OB/GYN requires maternity/delivery facilities",
    "severity": "HIGH",
    "flag_type": "MEDICAL_INCONSISTENCY"
  },
  {
    "pk_unique_id": "19",
    "facility_name": "Acrecity Medics",
    "facility_type": "clinic",
    "region": "Unknown",
    "city": "Accra",
    "claimed_specialty": "General Surgery",
    "specialty_key": "generalSurgery",
    "has_equipment": "False",
    "has_capability": "True",
    "has_procedure": "True",
    "reason": "Surgery requires an operating theatre and surgical equipment",
    "severity": "HIGH",
    "flag_type": "MEDICAL_INCONSISTENCY"
  },
  {
    "pk_unique_id": "503",
    "facility_name": "New Crystal Hospital",
    "facility_type": "hospital",
    "region": "Unknown",
    "city": "Ashaiman",
    "claimed_specialty": "Gynecology & Obstetrics",
    "specialty_key": "gynecologyAndObstetrics",
    "has_equipment": "False",
    "has_capability": "True",
    "has_procedure": "True",
    "reason": "OB/GYN requires maternity/delivery facilities",
    "severity": "HIGH",
    "flag_type": "MEDICAL_INCONSISTENCY"
  },
  {
    "pk_unique_id": "503",
    "facility_name": "New Crystal Hospital",
    "facility_type": "hospital",
    "region": "Unknown",
    "city": "Ashaiman",
    "claimed_specialty": "Pediatrics",
    "specialty_key": "pediatrics",
    "has_equipment": "False",
    "has_capability": "True",
    "has_procedure": "True",
    "reason": "Pediatrics requires child-specific care facilities",
    "severity": "HIGH",
    "flag_type": "MEDICAL_INCONSISTENCY"
  },
  {
    "pk_unique_id": "503",
    "facility_name": "New Crystal Hospital",
    "facility_type": "hospital",
    "region": "Unknown",
    "city": "Ashaiman",
    "claimed_specialty": "Pathology / Laboratory",
    "specialty_key": "pathology",
    "has_equipment": "False",
    "has_capability": "True",
    "has_procedure": "True",
    "reason": "Pathology requires laboratory facilities",
    "severity": "HIGH",
    "flag_type": "MEDICAL_INCONSISTENCY"
  },
  {
    "pk_unique_id": "770",
    "facility_name": "Vision Healthcare Clinic",
    "facility_type": "clinic",
    "region": "Greater Accra",
    "city": "Accra",
    "claimed_specialty": "Gynecology & Obstetrics",
    "specialty_key": "gynecologyAndObstetrics",
    "has_equipment": "True",
    "has_capability": "True",
    "has_procedure": "False",
    "reason": "OB/GYN requires maternity/delivery facilities",
    "severity": "HIGH",
    "flag_type": "MEDICAL_INCONSISTENCY"
  },
  {
    "pk_unique_id": "659",
    "facility_name": "St Benito Menni Hospital",
    "facility_type": "hospital",
    "region": "Ashanti",
    "city": "Dompoase",
    "claimed_specialty": "Ophthalmology",
    "specialty_key": "ophthalmology",
    "has_equipment": "True",
    "has_capability": "True",
    "has_procedure": "True",
    "reason": "Ophthalmology requires eye examination equipment",
    "severity": "HIGH",
    "flag_type": "MEDICAL_INCONSISTENCY"
  },
  {
    "pk_unique_id": "659",
    "facility_name": "St Benito Menni Hospital",
    "facility_type": "hospital",
    "region": "Ashanti",
    "city": "Dompoase",
    "claimed_specialty": "Gynecology & Obstetrics",
    "specialty_key": "gynecologyAndObstetrics",
    "has_equipment": "True",
    "has_capability": "True",
    "has_procedure": "True",
    "reason": "OB/GYN requires maternity/delivery facilities",
    "severity": "HIGH",
    "flag_type": "MEDICAL_INCONSISTENCY"
  },
  {
    "pk_unique_id": "659",
    "facility_name": "St Benito Menni Hospital",
    "facility_type": "hospital",
    "region": "Ashanti",
    "city": "Dompoase",
    "claimed_specialty": "Pediatrics",
    "specialty_key": "pediatrics",
    "has_equipment": "True",
    "has_capability": "True",
    "has_procedure": "True",
    "reason": "Pediatrics requires child-specific care facilities",
    "severity": "HIGH",
    "flag_type": "MEDICAL_INCONSISTENCY"
  },
  {
    "pk_unique_id": "355",
    "facility_name": "International Health Care Center Ghana",
    "facility_type": "clinic",
    "region": "Unknown",
    "city": "Accra",
    "claimed_specialty": "Infectious Diseases (incl. TB)",
    "specialty_key": "infectiousDiseases",
    "has_equipment": "False",
    "has_capability": "False",
    "has_procedure": "False",
    "reason": "Infectious disease care requires lab/testing or isolation facilities",
    "severity": "MEDIUM",
    "flag_type": "MEDICAL_INCONSISTENCY"
  },
  {
    "pk_unique_id": "359",
    "facility_name": "Jambo Medical Centre",
    "facility_type": "nan",
    "region": "Unknown",
    "city": "Accra",
    "claimed_specialty": "Radiology",
    "specialty_key": "radiology",
    "has_equipment": "True",
    "has_capability": "True",
    "has_procedure": "False",
    "reason": "Radiology requires imaging equipment",
    "severity": "HIGH",
    "flag_type": "MEDICAL_INCONSISTENCY"
  },
  {
    "pk_unique_id": "467",
    "facility_name": "MedTech Medical Center",
    "facility_type": "nan",
    "region": "Unknown",
    "city": "Accra",
    "claimed_specialty": "Gynecology & Obstetrics",
    "specialty_key": "gynecologyAndObstetrics",
    "has_equipment": "False",
    "has_capability": "True",
    "has_procedure": "False",
    "reason": "OB/GYN requires maternity/delivery facilities",
    "severity": "HIGH",
    "flag_type": "MEDICAL_INCONSISTENCY"
  },
  {
    "pk_unique_id": "191",
    "facility_name": "DEL International Hospital",
    "facility_type": "hospital",
    "region": "Greater Accra",
    "city": "Accra",
    "claimed_specialty": "Gynecology & Obstetrics",
    "specialty_key": "gynecologyAndObstetrics",
    "has_equipment": "True",
    "has_capability": "True",
    "has_procedure": "True",
    "reason": "OB/GYN requires maternity/delivery facilities",
    "severity": "HIGH",
    "flag_type": "MEDICAL_INCONSISTENCY"
  },
  {
    "pk_unique_id": "172",
    "facility_name": "Cosmopolitan Medical Centre",
    "facility_type": "hospital",
    "region": "Unknown",
    "city": "Accra",
    "claimed_specialty": "General Surgery",
    "specialty_key": "generalSurgery",
    "has_equipment": "False",
    "has_capability": "True",
    "has_procedure": "True",
    "reason": "Surgery requires an operating theatre and surgical equipment",
    "severity": "HIGH",
    "flag_type": "MEDICAL_INCONSISTENCY"
  },
  {
    "pk_unique_id": "172",
    "facility_name": "Cosmopolitan Medical Centre",
    "facility_type": "hospital",
    "region": "Unknown",
    "city": "Accra",
    "claimed_specialty": "Ophthalmology",
    "specialty_key": "ophthalmology",
    "has_equipment": "False",
    "has_capability": "True",
    "has_procedure": "True",
    "reason": "Ophthalmology requires eye examination equipment",
    "severity": "HIGH",
    "flag_type": "MEDICAL_INCONSISTENCY"
  },
  {
    "pk_unique_id": "633",
    "facility_name": "Sefwi Wiawso District Hospital",
    "facility_type": "hospital",
    "region": "Unknown",
    "city": "Sefwi Wiawso",
    "claimed_specialty": "Emergency Medicine",
    "specialty_key": "emergencyMedicine",
    "has_equipment": "False",
    "has_capability": "True",
    "has_procedure": "False",
    "reason": "Emergency medicine requires 24/7 emergency unit or ambulance",
    "severity": "HIGH",
    "flag_type": "MEDICAL_INCONSISTENCY"
  },
  {
    "pk_unique_id": "423",
    "facility_name": "Life Healthcare Center Ghana",
    "facility_type": "nan",
    "region": "Unknown",
    "city": "Accra",
    "claimed_specialty": "Ophthalmology",
    "specialty_key": "ophthalmology",
    "has_equipment": "False",
    "has_capability": "True",
    "has_procedure": "False",
    "reason": "Ophthalmology requires eye examination equipment",
    "severity": "HIGH",
    "flag_type": "MEDICAL_INCONSISTENCY"
  },
  {
    "pk_unique_id": "573",
    "facility_name": "Prime Diagnostics and Eye-care",
    "facility_type": "nan",
    "region": "Ashanti",
    "city": "Kumasi",
    "claimed_specialty": "Ophthalmology",
    "specialty_key": "ophthalmology",
    "has_equipment": "False",
    "has_capability": "True",
    "has_procedure": "False",
    "reason": "Ophthalmology requires eye examination equipment",
    "severity": "HIGH",
    "flag_type": "MEDICAL_INCONSISTENCY"
  },
  {
    "pk_unique_id": "311",
    "facility_name": "Gye Nyame Mobile Clinics",
    "facility_type": "nan",
    "region": "Unknown",
    "city": "Kumasi",
    "claimed_specialty": "Pediatrics",
    "specialty_key": "pediatrics",
    "has_equipment": "False",
    "has_capability": "True",
    "has_procedure": "True",
    "reason": "Pediatrics requires child-specific care facilities",
    "severity": "HIGH",
    "flag_type": "MEDICAL_INCONSISTENCY"
  },
  {
    "pk_unique_id": "312",
    "facility_name": "Habibi Herbal Hospital",
    "facility_type": "hospital",
    "region": "Unknown",
    "city": "Accra",
    "claimed_specialty": "Infectious Diseases (incl. TB)",
    "specialty_key": "infectiousDiseases",
    "has_equipment": "False",
    "has_capability": "True",
    "has_procedure": "True",
    "reason": "Infectious disease care requires lab/testing or isolation facilities",
    "severity": "HIGH",
    "flag_type": "MEDICAL_INCONSISTENCY"
  },
  {
    "pk_unique_id": "275",
    "facility_name": "Generational Health Foundation",
    "facility_type": "nan",
    "region": "Asokwa-Kumasi",
    "city": "Kumasi",
    "claimed_specialty": "General Surgery",
    "specialty_key": "generalSurgery",
    "has_equipment": "False",
    "has_capability": "False",
    "has_procedure": "False",
    "reason": "Surgery requires an operating theatre and surgical equipment",
    "severity": "MEDIUM",
    "flag_type": "MEDICAL_INCONSISTENCY"
  },
  {
    "pk_unique_id": "648",
    "facility_name": "Society for AIDS in Africa",
    "facility_type": "nan",
    "region": "Unknown",
    "city": "Accra",
    "claimed_specialty": "Infectious Diseases (incl. TB)",
    "specialty_key": "infectiousDiseases",
    "has_equipment": "False",
    "has_capability": "True",
    "has_procedure": "False",
    "reason": "Infectious disease care requires lab/testing or isolation facilities",
    "severity": "HIGH",
    "flag_type": "MEDICAL_INCONSISTENCY"
  },
  {
    "pk_unique_id": "46",
    "facility_name": "Akatsi South Municipal Hospital",
    "facility_type": "hospital",
    "region": "Unknown",
    "city": "Akatsi",
    "claimed_specialty": "Radiology",
    "specialty_key": "radiology",
    "has_equipment": "False",
    "has_capability": "True",
    "has_procedure": "True",
    "reason": "Radiology requires imaging equipment",
    "severity": "HIGH",
    "flag_type": "MEDICAL_INCONSISTENCY"
  },
  {
    "pk_unique_id": "211",
    "facility_name": "Dormaa Presbyterian Hospital",
    "facility_type": "hospital",
    "region": "Unknown",
    "city": "Dormaa Ahenkro",
    "claimed_specialty": "Pediatrics",
    "specialty_key": "pediatrics",
    "has_equipment": "False",
    "has_capability": "False",
    "has_procedure": "False",
    "reason": "Pediatrics requires child-specific care facilities",
    "severity": "MEDIUM",
    "flag_type": "MEDICAL_INCONSISTENCY"
  },
  {
    "pk_unique_id": "425",
    "facility_name": "Little Hearts Medical Practice",
    "facility_type": "nan",
    "region": "Unknown",
    "city": "Accra",
    "claimed_specialty": "Pediatrics",
    "specialty_key": "pediatrics",
    "has_equipment": "False",
    "has_capability": "False",
    "has_procedure": "False",
    "reason": "Pediatrics requires child-specific care facilities",
    "severity": "MEDIUM",
    "flag_type": "MEDICAL_INCONSISTENCY"
  },
  {
    "pk_unique_id": "428",
    "facility_name": "Lod Health Lounge",
    "facility_type": "nan",
    "region": "Unknown",
    "city": "Accra",
    "claimed_specialty": "Gynecology & Obstetrics",
    "specialty_key": "gynecologyAndObstetrics",
    "has_equipment": "False",
    "has_capability": "True",
    "has_procedure": "True",
    "reason": "OB/GYN requires maternity/delivery facilities",
    "severity": "HIGH",
    "flag_type": "MEDICAL_INCONSISTENCY"
  },
  {
    "pk_unique_id": "517",
    "facility_name": "Nyame Besa Herbal Clinic",
    "facility_type": "clinic",
    "region": "Unknown",
    "city": "Nsawam",
    "claimed_specialty": "Gynecology & Obstetrics",
    "specialty_key": "gynecologyAndObstetrics",
    "has_equipment": "False",
    "has_capability": "True",
    "has_procedure": "False",
    "reason": "OB/GYN requires maternity/delivery facilities",
    "severity": "HIGH",
    "flag_type": "MEDICAL_INCONSISTENCY"
  },
  {
    "pk_unique_id": "154",
    "facility_name": "Certa Medical Diagnostics",
    "facility_type": "clinic",
    "region": "Unknown",
    "city": "Accra",
    "claimed_specialty": "Gynecology & Obstetrics",
    "specialty_key": "gynecologyAndObstetrics",
    "has_equipment": "True",
    "has_capability": "True",
    "has_procedure": "True",
    "reason": "OB/GYN requires maternity/delivery facilities",
    "severity": "HIGH",
    "flag_type": "MEDICAL_INCONSISTENCY"
  },
  {
    "pk_unique_id": "656",
    "facility_name": "Spine and Nerve Center - Ghana",
    "facility_type": "clinic",
    "region": "Unknown",
    "city": "Accra",
    "claimed_specialty": "Neurosurgery",
    "specialty_key": "neurosurgery",
    "has_equipment": "False",
    "has_capability": "True",
    "has_procedure": "True",
    "reason": "Neurosurgery requires surgical facilities and neurosurgical equipment",
    "severity": "HIGH",
    "flag_type": "MEDICAL_INCONSISTENCY"
  },
  {
    "pk_unique_id": "129",
    "facility_name": "Bone Marrow Transplantation Ghana",
    "facility_type": "nan",
    "region": "Accra North",
    "city": "Accra",
    "claimed_specialty": "Pediatrics",
    "specialty_key": "pediatrics",
    "has_equipment": "False",
    "has_capability": "False",
    "has_procedure": "True",
    "reason": "Pediatrics requires child-specific care facilities",
    "severity": "HIGH",
    "flag_type": "MEDICAL_INCONSISTENCY"
  },
  {
    "pk_unique_id": "644",
    "facility_name": "Sisters Hospitallers' English Province",
    "facility_type": "nan",
    "region": "Ashanti",
    "city": "Dompoase",
    "claimed_specialty": "Cardiology",
    "specialty_key": "cardiology",
    "has_equipment": "False",
    "has_capability": "True",
    "has_procedure": "False",
    "reason": "Cardiology requires cardiac diagnostic equipment (ECG/echo)",
    "severity": "HIGH",
    "flag_type": "MEDICAL_INCONSISTENCY"
  },
  {
    "pk_unique_id": "644",
    "facility_name": "Sisters Hospitallers' English Province",
    "facility_type": "nan",
    "region": "Ashanti",
    "city": "Dompoase",
    "claimed_specialty": "Ophthalmology",
    "specialty_key": "ophthalmology",
    "has_equipment": "False",
    "has_capability": "True",
    "has_procedure": "False",
    "reason": "Ophthalmology requires eye examination equipment",
    "severity": "HIGH",
    "flag_type": "MEDICAL_INCONSISTENCY"
  },
  {
    "pk_unique_id": "644",
    "facility_name": "Sisters Hospitallers' English Province",
    "facility_type": "nan",
    "region": "Ashanti",
    "city": "Dompoase",
    "claimed_specialty": "Emergency Medicine",
    "specialty_key": "emergencyMedicine",
    "has_equipment": "False",
    "has_capability": "True",
    "has_procedure": "False",
    "reason": "Emergency medicine requires 24/7 emergency unit or ambulance",
    "severity": "HIGH",
    "flag_type": "MEDICAL_INCONSISTENCY"
  },
  {
    "pk_unique_id": "644",
    "facility_name": "Sisters Hospitallers' English Province",
    "facility_type": "nan",
    "region": "Ashanti",
    "city": "Dompoase",
    "claimed_specialty": "Gynecology & Obstetrics",
    "specialty_key": "gynecologyAndObstetrics",
    "has_equipment": "False",
    "has_capability": "True",
    "has_procedure": "False",
    "reason": "OB/GYN requires maternity/delivery facilities",
    "severity": "HIGH",
    "flag_type": "MEDICAL_INCONSISTENCY"
  },
  {
    "pk_unique_id": "644",
    "facility_name": "Sisters Hospitallers' English Province",
    "facility_type": "nan",
    "region": "Ashanti",
    "city": "Dompoase",
    "claimed_specialty": "Pediatrics",
    "specialty_key": "pediatrics",
    "has_equipment": "False",
    "has_capability": "True",
    "has_procedure": "False",
    "reason": "Pediatrics requires child-specific care facilities",
    "severity": "HIGH",
    "flag_type": "MEDICAL_INCONSISTENCY"
  },
  {
    "pk_unique_id": "644",
    "facility_name": "Sisters Hospitallers' English Province",
    "facility_type": "nan",
    "region": "Ashanti",
    "city": "Dompoase",
    "claimed_specialty": "Pathology / Laboratory",
    "specialty_key": "pathology",
    "has_equipment": "False",
    "has_capability": "True",
    "has_procedure": "False",
    "reason": "Pathology requires laboratory facilities",
    "severity": "HIGH",
    "flag_type": "MEDICAL_INCONSISTENCY"
  },
  {
    "pk_unique_id": "488",
    "facility_name": "Modern Way Herbal Clinic",
    "facility_type": "hospital",
    "region": "Unknown",
    "city": "Sunyani",
    "claimed_specialty": "Gynecology & Obstetrics",
    "specialty_key": "gynecologyAndObstetrics",
    "has_equipment": "False",
    "has_capability": "True",
    "has_procedure": "False",
    "reason": "OB/GYN requires maternity/delivery facilities",
    "severity": "HIGH",
    "flag_type": "MEDICAL_INCONSISTENCY"
  },
  {
    "pk_unique_id": "703",
    "facility_name": "Supercare Specialist Medical & Ho Fertility Center",
    "facility_type": "hospital",
    "region": "Unknown",
    "city": "Ho",
    "claimed_specialty": "Gynecology & Obstetrics",
    "specialty_key": "gynecologyAndObstetrics",
    "has_equipment": "False",
    "has_capability": "True",
    "has_procedure": "False",
    "reason": "OB/GYN requires maternity/delivery facilities",
    "severity": "HIGH",
    "flag_type": "MEDICAL_INCONSISTENCY"
  },
  {
    "pk_unique_id": "301",
    "facility_name": "GPHA Clinic",
    "facility_type": "clinic",
    "region": "Unknown",
    "city": "Takoradi",
    "claimed_specialty": "Gynecology & Obstetrics",
    "specialty_key": "gynecologyAndObstetrics",
    "has_equipment": "False",
    "has_capability": "True",
    "has_procedure": "False",
    "reason": "OB/GYN requires maternity/delivery facilities",
    "severity": "HIGH",
    "flag_type": "MEDICAL_INCONSISTENCY"
  },
  {
    "pk_unique_id": "536",
    "facility_name": "Ospedale Didattico di Tamale",
    "facility_type": "hospital",
    "region": "Northern",
    "city": "Tamale",
    "claimed_specialty": "Nephrology",
    "specialty_key": "nephrology",
    "has_equipment": "True",
    "has_capability": "True",
    "has_procedure": "True",
    "reason": "Nephrology requires dialysis or renal care facilities",
    "severity": "HIGH",
    "flag_type": "MEDICAL_INCONSISTENCY"
  },
  {
    "pk_unique_id": "536",
    "facility_name": "Ospedale Didattico di Tamale",
    "facility_type": "hospital",
    "region": "Northern",
    "city": "Tamale",
    "claimed_specialty": "Critical Care / ICU",
    "specialty_key": "criticalCareMedicine",
    "has_equipment": "True",
    "has_capability": "True",
    "has_procedure": "True",
    "reason": "Critical care requires ICU / intensive care unit",
    "severity": "HIGH",
    "flag_type": "MEDICAL_INCONSISTENCY"
  },
  {
    "pk_unique_id": "385",
    "facility_name": "KK Health CARE Center",
    "facility_type": "hospital",
    "region": "Unknown",
    "city": "Swedru",
    "claimed_specialty": "Gynecology & Obstetrics",
    "specialty_key": "gynecologyAndObstetrics",
    "has_equipment": "False",
    "has_capability": "True",
    "has_procedure": "False",
    "reason": "OB/GYN requires maternity/delivery facilities",
    "severity": "HIGH",
    "flag_type": "MEDICAL_INCONSISTENCY"
  },
  {
    "pk_unique_id": "152",
    "facility_name": "Central Regional Police Clinic",
    "facility_type": "nan",
    "region": "Unknown",
    "city": "Ghana",
    "claimed_specialty": "General Surgery",
    "specialty_key": "generalSurgery",
    "has_equipment": "False",
    "has_capability": "False",
    "has_procedure": "False",
    "reason": "Surgery requires an operating theatre and surgical equipment",
    "severity": "MEDIUM",
    "flag_type": "MEDICAL_INCONSISTENCY"
  },
  {
    "pk_unique_id": "152",
    "facility_name": "Central Regional Police Clinic",
    "facility_type": "nan",
    "region": "Unknown",
    "city": "Ghana",
    "claimed_specialty": "Ophthalmology",
    "specialty_key": "ophthalmology",
    "has_equipment": "False",
    "has_capability": "False",
    "has_procedure": "False",
    "reason": "Ophthalmology requires eye examination equipment",
    "severity": "MEDIUM",
    "flag_type": "MEDICAL_INCONSISTENCY"
  },
  {
    "pk_unique_id": "152",
    "facility_name": "Central Regional Police Clinic",
    "facility_type": "nan",
    "region": "Unknown",
    "city": "Ghana",
    "claimed_specialty": "Radiology",
    "specialty_key": "radiology",
    "has_equipment": "False",
    "has_capability": "False",
    "has_procedure": "False",
    "reason": "Radiology requires imaging equipment",
    "severity": "MEDIUM",
    "flag_type": "MEDICAL_INCONSISTENCY"
  },
  {
    "pk_unique_id": "152",
    "facility_name": "Central Regional Police Clinic",
    "facility_type": "nan",
    "region": "Unknown",
    "city": "Ghana",
    "claimed_specialty": "Emergency Medicine",
    "specialty_key": "emergencyMedicine",
    "has_equipment": "False",
    "has_capability": "False",
    "has_procedure": "False",
    "reason": "Emergency medicine requires 24/7 emergency unit or ambulance",
    "severity": "MEDIUM",
    "flag_type": "MEDICAL_INCONSISTENCY"
  },
  {
    "pk_unique_id": "152",
    "facility_name": "Central Regional Police Clinic",
    "facility_type": "nan",
    "region": "Unknown",
    "city": "Ghana",
    "claimed_specialty": "Gynecology & Obstetrics",
    "specialty_key": "gynecologyAndObstetrics",
    "has_equipment": "False",
    "has_capability": "False",
    "has_procedure": "False",
    "reason": "OB/GYN requires maternity/delivery facilities",
    "severity": "MEDIUM",
    "flag_type": "MEDICAL_INCONSISTENCY"
  },
  {
    "pk_unique_id": "152",
    "facility_name": "Central Regional Police Clinic",
    "facility_type": "nan",
    "region": "Unknown",
    "city": "Ghana",
    "claimed_specialty": "Pediatrics",
    "specialty_key": "pediatrics",
    "has_equipment": "False",
    "has_capability": "False",
    "has_procedure": "False",
    "reason": "Pediatrics requires child-specific care facilities",
    "severity": "MEDIUM",
    "flag_type": "MEDICAL_INCONSISTENCY"
  },
  {
    "pk_unique_id": "152",
    "facility_name": "Central Regional Police Clinic",
    "facility_type": "nan",
    "region": "Unknown",
    "city": "Ghana",
    "claimed_specialty": "Pathology / Laboratory",
    "specialty_key": "pathology",
    "has_equipment": "False",
    "has_capability": "False",
    "has_procedure": "False",
    "reason": "Pathology requires laboratory facilities",
    "severity": "MEDIUM",
    "flag_type": "MEDICAL_INCONSISTENCY"
  },
  {
    "pk_unique_id": "430",
    "facility_name": "Luke Society Ghana",
    "facility_type": "nan",
    "region": "Ashanti",
    "city": "Kasei (via Ejura)",
    "claimed_specialty": "General Surgery",
    "specialty_key": "generalSurgery",
    "has_equipment": "False",
    "has_capability": "False",
    "has_procedure": "False",
    "reason": "Surgery requires an operating theatre and surgical equipment",
    "severity": "MEDIUM",
    "flag_type": "MEDICAL_INCONSISTENCY"
  },
  {
    "pk_unique_id": "430",
    "facility_name": "Luke Society Ghana",
    "facility_type": "nan",
    "region": "Ashanti",
    "city": "Kasei (via Ejura)",
    "claimed_specialty": "Ophthalmology",
    "specialty_key": "ophthalmology",
    "has_equipment": "False",
    "has_capability": "False",
    "has_procedure": "False",
    "reason": "Ophthalmology requires eye examination equipment",
    "severity": "MEDIUM",
    "flag_type": "MEDICAL_INCONSISTENCY"
  },
  {
    "pk_unique_id": "430",
    "facility_name": "Luke Society Ghana",
    "facility_type": "nan",
    "region": "Ashanti",
    "city": "Kasei (via Ejura)",
    "claimed_specialty": "Radiology",
    "specialty_key": "radiology",
    "has_equipment": "False",
    "has_capability": "False",
    "has_procedure": "False",
    "reason": "Radiology requires imaging equipment",
    "severity": "MEDIUM",
    "flag_type": "MEDICAL_INCONSISTENCY"
  },
  {
    "pk_unique_id": "430",
    "facility_name": "Luke Society Ghana",
    "facility_type": "nan",
    "region": "Ashanti",
    "city": "Kasei (via Ejura)",
    "claimed_specialty": "Emergency Medicine",
    "specialty_key": "emergencyMedicine",
    "has_equipment": "False",
    "has_capability": "False",
    "has_procedure": "False",
    "reason": "Emergency medicine requires 24/7 emergency unit or ambulance",
    "severity": "MEDIUM",
    "flag_type": "MEDICAL_INCONSISTENCY"
  },
  {
    "pk_unique_id": "430",
    "facility_name": "Luke Society Ghana",
    "facility_type": "nan",
    "region": "Ashanti",
    "city": "Kasei (via Ejura)",
    "claimed_specialty": "Infectious Diseases (incl. TB)",
    "specialty_key": "infectiousDiseases",
    "has_equipment": "False",
    "has_capability": "False",
    "has_procedure": "False",
    "reason": "Infectious disease care requires lab/testing or isolation facilities",
    "severity": "MEDIUM",
    "flag_type": "MEDICAL_INCONSISTENCY"
  },
  {
    "pk_unique_id": "430",
    "facility_name": "Luke Society Ghana",
    "facility_type": "nan",
    "region": "Ashanti",
    "city": "Kasei (via Ejura)",
    "claimed_specialty": "Gynecology & Obstetrics",
    "specialty_key": "gynecologyAndObstetrics",
    "has_equipment": "False",
    "has_capability": "False",
    "has_procedure": "False",
    "reason": "OB/GYN requires maternity/delivery facilities",
    "severity": "MEDIUM",
    "flag_type": "MEDICAL_INCONSISTENCY"
  },
  {
    "pk_unique_id": "430",
    "facility_name": "Luke Society Ghana",
    "facility_type": "nan",
    "region": "Ashanti",
    "city": "Kasei (via Ejura)",
    "claimed_specialty": "Pediatrics",
    "specialty_key": "pediatrics",
    "has_equipment": "False",
    "has_capability": "False",
    "has_procedure": "False",
    "reason": "Pediatrics requires child-specific care facilities",
    "severity": "MEDIUM",
    "flag_type": "MEDICAL_INCONSISTENCY"
  },
  {
    "pk_unique_id": "430",
    "facility_name": "Luke Society Ghana",
    "facility_type": "nan",
    "region": "Ashanti",
    "city": "Kasei (via Ejura)",
    "claimed_specialty": "Pathology / Laboratory",
    "specialty_key": "pathology",
    "has_equipment": "False",
    "has_capability": "False",
    "has_procedure": "False",
    "reason": "Pathology requires laboratory facilities",
    "severity": "MEDIUM",
    "flag_type": "MEDICAL_INCONSISTENCY"
  },
  {
    "pk_unique_id": "185",
    "facility_name": "Dar-Bem Clinic",
    "facility_type": "clinic",
    "region": "Greater Accra",
    "city": "Ashaiman",
    "claimed_specialty": "Gynecology & Obstetrics",
    "specialty_key": "gynecologyAndObstetrics",
    "has_equipment": "False",
    "has_capability": "True",
    "has_procedure": "False",
    "reason": "OB/GYN requires maternity/delivery facilities",
    "severity": "HIGH",
    "flag_type": "MEDICAL_INCONSISTENCY"
  },
  {
    "pk_unique_id": "188",
    "facility_name": "Datwell_Medical",
    "facility_type": "nan",
    "region": "Unknown",
    "city": "Accra",
    "claimed_specialty": "Pediatrics",
    "specialty_key": "pediatrics",
    "has_equipment": "False",
    "has_capability": "False",
    "has_procedure": "False",
    "reason": "Pediatrics requires child-specific care facilities",
    "severity": "MEDIUM",
    "flag_type": "MEDICAL_INCONSISTENCY"
  },
  {
    "pk_unique_id": "72",
    "facility_name": "Ankaful Leprosy & General Hospital",
    "facility_type": "hospital",
    "region": "Keea",
    "city": "Ankaful",
    "claimed_specialty": "Infectious Diseases (incl. TB)",
    "specialty_key": "infectiousDiseases",
    "has_equipment": "False",
    "has_capability": "True",
    "has_procedure": "False",
    "reason": "Infectious disease care requires lab/testing or isolation facilities",
    "severity": "HIGH",
    "flag_type": "MEDICAL_INCONSISTENCY"
  },
  {
    "pk_unique_id": "419",
    "facility_name": "Le Mete NGO Ghana",
    "facility_type": "nan",
    "region": "Unknown",
    "city": "Tamale",
    "claimed_specialty": "Nephrology",
    "specialty_key": "nephrology",
    "has_equipment": "True",
    "has_capability": "True",
    "has_procedure": "True",
    "reason": "Nephrology requires dialysis or renal care facilities",
    "severity": "HIGH",
    "flag_type": "MEDICAL_INCONSISTENCY"
  },
  {
    "pk_unique_id": "419",
    "facility_name": "Le Mete NGO Ghana",
    "facility_type": "nan",
    "region": "Unknown",
    "city": "Tamale",
    "claimed_specialty": "Critical Care / ICU",
    "specialty_key": "criticalCareMedicine",
    "has_equipment": "True",
    "has_capability": "True",
    "has_procedure": "True",
    "reason": "Critical care requires ICU / intensive care unit",
    "severity": "HIGH",
    "flag_type": "MEDICAL_INCONSISTENCY"
  },
  {
    "pk_unique_id": "419",
    "facility_name": "Le Mete NGO Ghana",
    "facility_type": "nan",
    "region": "Unknown",
    "city": "Tamale",
    "claimed_specialty": "Pathology / Laboratory",
    "specialty_key": "pathology",
    "has_equipment": "True",
    "has_capability": "True",
    "has_procedure": "True",
    "reason": "Pathology requires laboratory facilities",
    "severity": "HIGH",
    "flag_type": "MEDICAL_INCONSISTENCY"
  },
  {
    "pk_unique_id": "584",
    "facility_name": "Quest Medical Imaging",
    "facility_type": "nan",
    "region": "Greater Accra",
    "city": "Accra",
    "claimed_specialty": "Cardiology",
    "specialty_key": "cardiology",
    "has_equipment": "False",
    "has_capability": "True",
    "has_procedure": "True",
    "reason": "Cardiology requires cardiac diagnostic equipment (ECG/echo)",
    "severity": "HIGH",
    "flag_type": "MEDICAL_INCONSISTENCY"
  },
  {
    "pk_unique_id": "584",
    "facility_name": "Quest Medical Imaging",
    "facility_type": "nan",
    "region": "Greater Accra",
    "city": "Accra",
    "claimed_specialty": "Critical Care / ICU",
    "specialty_key": "criticalCareMedicine",
    "has_equipment": "False",
    "has_capability": "True",
    "has_procedure": "True",
    "reason": "Critical care requires ICU / intensive care unit",
    "severity": "HIGH",
    "flag_type": "MEDICAL_INCONSISTENCY"
  },
  {
    "pk_unique_id": "584",
    "facility_name": "Quest Medical Imaging",
    "facility_type": "nan",
    "region": "Greater Accra",
    "city": "Accra",
    "claimed_specialty": "Pediatrics",
    "specialty_key": "pediatrics",
    "has_equipment": "False",
    "has_capability": "True",
    "has_procedure": "True",
    "reason": "Pediatrics requires child-specific care facilities",
    "severity": "HIGH",
    "flag_type": "MEDICAL_INCONSISTENCY"
  },
  {
    "pk_unique_id": "106",
    "facility_name": "Baptist Medical Centre",
    "facility_type": "hospital",
    "region": "Unknown",
    "city": "Nalerigu",
    "claimed_specialty": "Gynecology & Obstetrics",
    "specialty_key": "gynecologyAndObstetrics",
    "has_equipment": "False",
    "has_capability": "True",
    "has_procedure": "False",
    "reason": "OB/GYN requires maternity/delivery facilities",
    "severity": "HIGH",
    "flag_type": "MEDICAL_INCONSISTENCY"
  },
  {
    "pk_unique_id": "13",
    "facility_name": "Accra Newtown Islamic Hospital",
    "facility_type": "hospital",
    "region": "Unknown",
    "city": "Accra Newtown",
    "claimed_specialty": "Ophthalmology",
    "specialty_key": "ophthalmology",
    "has_equipment": "True",
    "has_capability": "True",
    "has_procedure": "True",
    "reason": "Ophthalmology requires eye examination equipment",
    "severity": "HIGH",
    "flag_type": "MEDICAL_INCONSISTENCY"
  },
  {
    "pk_unique_id": "3",
    "facility_name": "2BN Military Hospital",
    "facility_type": "hospital",
    "region": "Western",
    "city": "Apremdo",
    "claimed_specialty": "Emergency Medicine",
    "specialty_key": "emergencyMedicine",
    "has_equipment": "False",
    "has_capability": "False",
    "has_procedure": "False",
    "reason": "Emergency medicine requires 24/7 emergency unit or ambulance",
    "severity": "MEDIUM",
    "flag_type": "MEDICAL_INCONSISTENCY"
  },
  {
    "pk_unique_id": "427",
    "facility_name": "Lizzie's Maternity Home",
    "facility_type": "nan",
    "region": "Unknown",
    "city": "",
    "claimed_specialty": "Gynecology & Obstetrics",
    "specialty_key": "gynecologyAndObstetrics",
    "has_equipment": "False",
    "has_capability": "False",
    "has_procedure": "False",
    "reason": "OB/GYN requires maternity/delivery facilities",
    "severity": "MEDIUM",
    "flag_type": "MEDICAL_INCONSISTENCY"
  },
  {
    "pk_unique_id": "506",
    "facility_name": "New Life Hospital",
    "facility_type": "hospital",
    "region": "Unknown",
    "city": "Adoagyiri-adeiso",
    "claimed_specialty": "Emergency Medicine",
    "specialty_key": "emergencyMedicine",
    "has_equipment": "False",
    "has_capability": "True",
    "has_procedure": "False",
    "reason": "Emergency medicine requires 24/7 emergency unit or ambulance",
    "severity": "HIGH",
    "flag_type": "MEDICAL_INCONSISTENCY"
  },
  {
    "pk_unique_id": "144",
    "facility_name": "Cape Coast Teaching Hospital",
    "facility_type": "hospital",
    "region": "Unknown",
    "city": "Tamale",
    "claimed_specialty": "General Surgery",
    "specialty_key": "generalSurgery",
    "has_equipment": "False",
    "has_capability": "False",
    "has_procedure": "False",
    "reason": "Surgery requires an operating theatre and surgical equipment",
    "severity": "MEDIUM",
    "flag_type": "MEDICAL_INCONSISTENCY"
  },
  {
    "pk_unique_id": "144",
    "facility_name": "Cape Coast Teaching Hospital",
    "facility_type": "hospital",
    "region": "Unknown",
    "city": "Tamale",
    "claimed_specialty": "Ophthalmology",
    "specialty_key": "ophthalmology",
    "has_equipment": "False",
    "has_capability": "False",
    "has_procedure": "False",
    "reason": "Ophthalmology requires eye examination equipment",
    "severity": "MEDIUM",
    "flag_type": "MEDICAL_INCONSISTENCY"
  },
  {
    "pk_unique_id": "144",
    "facility_name": "Cape Coast Teaching Hospital",
    "facility_type": "hospital",
    "region": "Unknown",
    "city": "Tamale",
    "claimed_specialty": "Radiology",
    "specialty_key": "radiology",
    "has_equipment": "False",
    "has_capability": "False",
    "has_procedure": "False",
    "reason": "Radiology requires imaging equipment",
    "severity": "MEDIUM",
    "flag_type": "MEDICAL_INCONSISTENCY"
  },
  {
    "pk_unique_id": "144",
    "facility_name": "Cape Coast Teaching Hospital",
    "facility_type": "hospital",
    "region": "Unknown",
    "city": "Tamale",
    "claimed_specialty": "Emergency Medicine",
    "specialty_key": "emergencyMedicine",
    "has_equipment": "False",
    "has_capability": "False",
    "has_procedure": "False",
    "reason": "Emergency medicine requires 24/7 emergency unit or ambulance",
    "severity": "MEDIUM",
    "flag_type": "MEDICAL_INCONSISTENCY"
  },
  {
    "pk_unique_id": "144",
    "facility_name": "Cape Coast Teaching Hospital",
    "facility_type": "hospital",
    "region": "Unknown",
    "city": "Tamale",
    "claimed_specialty": "Gynecology & Obstetrics",
    "specialty_key": "gynecologyAndObstetrics",
    "has_equipment": "False",
    "has_capability": "False",
    "has_procedure": "False",
    "reason": "OB/GYN requires maternity/delivery facilities",
    "severity": "MEDIUM",
    "flag_type": "MEDICAL_INCONSISTENCY"
  },
  {
    "pk_unique_id": "144",
    "facility_name": "Cape Coast Teaching Hospital",
    "facility_type": "hospital",
    "region": "Unknown",
    "city": "Tamale",
    "claimed_specialty": "Pediatrics",
    "specialty_key": "pediatrics",
    "has_equipment": "False",
    "has_capability": "False",
    "has_procedure": "False",
    "reason": "Pediatrics requires child-specific care facilities",
    "severity": "MEDIUM",
    "flag_type": "MEDICAL_INCONSISTENCY"
  },
  {
    "pk_unique_id": "144",
    "facility_name": "Cape Coast Teaching Hospital",
    "facility_type": "hospital",
    "region": "Unknown",
    "city": "Tamale",
    "claimed_specialty": "Pathology / Laboratory",
    "specialty_key": "pathology",
    "has_equipment": "False",
    "has_capability": "False",
    "has_procedure": "False",
    "reason": "Pathology requires laboratory facilities",
    "severity": "MEDIUM",
    "flag_type": "MEDICAL_INCONSISTENCY"
  },
  {
    "pk_unique_id": "541",
    "facility_name": "Owusu Memorial Hospital",
    "facility_type": "hospital",
    "region": "Unknown",
    "city": "Sunyani",
    "claimed_specialty": "Gynecology & Obstetrics",
    "specialty_key": "gynecologyAndObstetrics",
    "has_equipment": "False",
    "has_capability": "True",
    "has_procedure": "False",
    "reason": "OB/GYN requires maternity/delivery facilities",
    "severity": "HIGH",
    "flag_type": "MEDICAL_INCONSISTENCY"
  },
  {
    "pk_unique_id": "157",
    "facility_name": "Children's Hospital, Okomfo Anokye Road, Kumasi, Ghana",
    "facility_type": "hospital",
    "region": "Unknown",
    "city": "Kumasi",
    "claimed_specialty": "Gynecology & Obstetrics",
    "specialty_key": "gynecologyAndObstetrics",
    "has_equipment": "False",
    "has_capability": "True",
    "has_procedure": "False",
    "reason": "OB/GYN requires maternity/delivery facilities",
    "severity": "HIGH",
    "flag_type": "MEDICAL_INCONSISTENCY"
  },
  {
    "pk_unique_id": "214",
    "facility_name": "Dr. Power Herbal Clinic TV",
    "facility_type": "nan",
    "region": "Unknown",
    "city": "Accra",
    "claimed_specialty": "Infectious Diseases (incl. TB)",
    "specialty_key": "infectiousDiseases",
    "has_equipment": "False",
    "has_capability": "True",
    "has_procedure": "False",
    "reason": "Infectious disease care requires lab/testing or isolation facilities",
    "severity": "HIGH",
    "flag_type": "MEDICAL_INCONSISTENCY"
  },
  {
    "pk_unique_id": "214",
    "facility_name": "Dr. Power Herbal Clinic TV",
    "facility_type": "nan",
    "region": "Unknown",
    "city": "Accra",
    "claimed_specialty": "Gynecology & Obstetrics",
    "specialty_key": "gynecologyAndObstetrics",
    "has_equipment": "False",
    "has_capability": "True",
    "has_procedure": "False",
    "reason": "OB/GYN requires maternity/delivery facilities",
    "severity": "HIGH",
    "flag_type": "MEDICAL_INCONSISTENCY"
  },
  {
    "pk_unique_id": "32",
    "facility_name": "African Vision Clinic - Adenta Housing down, Accra, Ghana",
    "facility_type": "clinic",
    "region": "Unknown",
    "city": "Accra",
    "claimed_specialty": "Ophthalmology",
    "specialty_key": "ophthalmology",
    "has_equipment": "False",
    "has_capability": "True",
    "has_procedure": "False",
    "reason": "Ophthalmology requires eye examination equipment",
    "severity": "HIGH",
    "flag_type": "MEDICAL_INCONSISTENCY"
  },
  {
    "pk_unique_id": "230",
    "facility_name": "Emmanuel Eye Clinic - Shiashie",
    "facility_type": "clinic",
    "region": "Unknown",
    "city": "Accra",
    "claimed_specialty": "Ophthalmology",
    "specialty_key": "ophthalmology",
    "has_equipment": "False",
    "has_capability": "True",
    "has_procedure": "False",
    "reason": "Ophthalmology requires eye examination equipment",
    "severity": "HIGH",
    "flag_type": "MEDICAL_INCONSISTENCY"
  },
  {
    "pk_unique_id": "198",
    "facility_name": "Digestive Diseases Aid",
    "facility_type": "nan",
    "region": "Unknown",
    "city": "",
    "claimed_specialty": "Infectious Diseases (incl. TB)",
    "specialty_key": "infectiousDiseases",
    "has_equipment": "False",
    "has_capability": "True",
    "has_procedure": "False",
    "reason": "Infectious disease care requires lab/testing or isolation facilities",
    "severity": "HIGH",
    "flag_type": "MEDICAL_INCONSISTENCY"
  },
  {
    "pk_unique_id": "198",
    "facility_name": "Digestive Diseases Aid",
    "facility_type": "nan",
    "region": "Unknown",
    "city": "",
    "claimed_specialty": "Gynecology & Obstetrics",
    "specialty_key": "gynecologyAndObstetrics",
    "has_equipment": "False",
    "has_capability": "True",
    "has_procedure": "False",
    "reason": "OB/GYN requires maternity/delivery facilities",
    "severity": "HIGH",
    "flag_type": "MEDICAL_INCONSISTENCY"
  },
  {
    "pk_unique_id": "615",
    "facility_name": "Saint Johns Clinic and Maternity Home Company",
    "facility_type": "clinic",
    "region": "Unknown",
    "city": "Cape Coast",
    "claimed_specialty": "Gynecology & Obstetrics",
    "specialty_key": "gynecologyAndObstetrics",
    "has_equipment": "False",
    "has_capability": "True",
    "has_procedure": "False",
    "reason": "OB/GYN requires maternity/delivery facilities",
    "severity": "HIGH",
    "flag_type": "MEDICAL_INCONSISTENCY"
  },
  {
    "pk_unique_id": "642",
    "facility_name": "Sincere Herbal Research and Treatment Center",
    "facility_type": "clinic",
    "region": "Unknown",
    "city": "Kintampo",
    "claimed_specialty": "Infectious Diseases (incl. TB)",
    "specialty_key": "infectiousDiseases",
    "has_equipment": "False",
    "has_capability": "True",
    "has_procedure": "False",
    "reason": "Infectious disease care requires lab/testing or isolation facilities",
    "severity": "HIGH",
    "flag_type": "MEDICAL_INCONSISTENCY"
  },
  {
    "pk_unique_id": "148",
    "facility_name": "Catholic Health Service Trust, Ghana",
    "facility_type": "nan",
    "region": "Unknown",
    "city": "Accra",
    "claimed_specialty": "Gynecology & Obstetrics",
    "specialty_key": "gynecologyAndObstetrics",
    "has_equipment": "False",
    "has_capability": "True",
    "has_procedure": "False",
    "reason": "OB/GYN requires maternity/delivery facilities",
    "severity": "HIGH",
    "flag_type": "MEDICAL_INCONSISTENCY"
  },
  {
    "pk_unique_id": "148",
    "facility_name": "Catholic Health Service Trust, Ghana",
    "facility_type": "nan",
    "region": "Unknown",
    "city": "Accra",
    "claimed_specialty": "Pediatrics",
    "specialty_key": "pediatrics",
    "has_equipment": "False",
    "has_capability": "True",
    "has_procedure": "False",
    "reason": "Pediatrics requires child-specific care facilities",
    "severity": "HIGH",
    "flag_type": "MEDICAL_INCONSISTENCY"
  },
  {
    "pk_unique_id": "376",
    "facility_name": "Kate Afram Clinic",
    "facility_type": "clinic",
    "region": "Unknown",
    "city": "",
    "claimed_specialty": "Gynecology & Obstetrics",
    "specialty_key": "gynecologyAndObstetrics",
    "has_equipment": "False",
    "has_capability": "True",
    "has_procedure": "False",
    "reason": "OB/GYN requires maternity/delivery facilities",
    "severity": "HIGH",
    "flag_type": "MEDICAL_INCONSISTENCY"
  },
  {
    "pk_unique_id": "341",
    "facility_name": "IAMA Diagnostic Ultrasound & Medical Centre",
    "facility_type": "nan",
    "region": "Unknown",
    "city": "Kumasi",
    "claimed_specialty": "Radiology",
    "specialty_key": "radiology",
    "has_equipment": "False",
    "has_capability": "False",
    "has_procedure": "False",
    "reason": "Radiology requires imaging equipment",
    "severity": "MEDIUM",
    "flag_type": "MEDICAL_INCONSISTENCY"
  },
  {
    "pk_unique_id": "371",
    "facility_name": "Jubile Catholic Children Hospital",
    "facility_type": "hospital",
    "region": "Western",
    "city": "Apowa",
    "claimed_specialty": "Pediatrics",
    "specialty_key": "pediatrics",
    "has_equipment": "False",
    "has_capability": "False",
    "has_procedure": "False",
    "reason": "Pediatrics requires child-specific care facilities",
    "severity": "MEDIUM",
    "flag_type": "MEDICAL_INCONSISTENCY"
  },
  {
    "pk_unique_id": "485",
    "facility_name": "Mizprom Herbal Centre",
    "facility_type": "clinic",
    "region": "Unknown",
    "city": "Accra",
    "claimed_specialty": "Infectious Diseases (incl. TB)",
    "specialty_key": "infectiousDiseases",
    "has_equipment": "False",
    "has_capability": "False",
    "has_procedure": "False",
    "reason": "Infectious disease care requires lab/testing or isolation facilities",
    "severity": "MEDIUM",
    "flag_type": "MEDICAL_INCONSISTENCY"
  },
  {
    "pk_unique_id": "456",
    "facility_name": "MEDHealth Centers",
    "facility_type": "nan",
    "region": "Unknown",
    "city": "Accra",
    "claimed_specialty": "Gynecology & Obstetrics",
    "specialty_key": "gynecologyAndObstetrics",
    "has_equipment": "False",
    "has_capability": "True",
    "has_procedure": "True",
    "reason": "OB/GYN requires maternity/delivery facilities",
    "severity": "HIGH",
    "flag_type": "MEDICAL_INCONSISTENCY"
  },
  {
    "pk_unique_id": "63",
    "facility_name": "Amang Health Centre",
    "facility_type": "clinic",
    "region": "Unknown",
    "city": "",
    "claimed_specialty": "Cardiology",
    "specialty_key": "cardiology",
    "has_equipment": "False",
    "has_capability": "True",
    "has_procedure": "False",
    "reason": "Cardiology requires cardiac diagnostic equipment (ECG/echo)",
    "severity": "HIGH",
    "flag_type": "MEDICAL_INCONSISTENCY"
  },
  {
    "pk_unique_id": "63",
    "facility_name": "Amang Health Centre",
    "facility_type": "clinic",
    "region": "Unknown",
    "city": "",
    "claimed_specialty": "Nephrology",
    "specialty_key": "nephrology",
    "has_equipment": "False",
    "has_capability": "True",
    "has_procedure": "False",
    "reason": "Nephrology requires dialysis or renal care facilities",
    "severity": "HIGH",
    "flag_type": "MEDICAL_INCONSISTENCY"
  },
  {
    "pk_unique_id": "789",
    "facility_name": "Women's Health Clinic - House # opposite zenith hotel Takoradi, Takoradi, Ghana",
    "facility_type": "clinic",
    "region": "Unknown",
    "city": "Takoradi",
    "claimed_specialty": "Gynecology & Obstetrics",
    "specialty_key": "gynecologyAndObstetrics",
    "has_equipment": "False",
    "has_capability": "True",
    "has_procedure": "False",
    "reason": "OB/GYN requires maternity/delivery facilities",
    "severity": "HIGH",
    "flag_type": "MEDICAL_INCONSISTENCY"
  },
  {
    "pk_unique_id": "705",
    "facility_name": "SVG Africa",
    "facility_type": "nan",
    "region": "Unknown",
    "city": "",
    "claimed_specialty": "General Surgery",
    "specialty_key": "generalSurgery",
    "has_equipment": "False",
    "has_capability": "True",
    "has_procedure": "True",
    "reason": "Surgery requires an operating theatre and surgical equipment",
    "severity": "HIGH",
    "flag_type": "MEDICAL_INCONSISTENCY"
  },
  {
    "pk_unique_id": "649",
    "facility_name": "Sogakope - MDC",
    "facility_type": "clinic",
    "region": "Unknown",
    "city": "Sogakope",
    "claimed_specialty": "Radiology",
    "specialty_key": "radiology",
    "has_equipment": "False",
    "has_capability": "False",
    "has_procedure": "False",
    "reason": "Radiology requires imaging equipment",
    "severity": "MEDIUM",
    "flag_type": "MEDICAL_INCONSISTENCY"
  },
  {
    "pk_unique_id": "710",
    "facility_name": "Synlab Ghana (Kumasi Ahodwo Depot)",
    "facility_type": "nan",
    "region": "Unknown",
    "city": "Kumasi",
    "claimed_specialty": "Pathology / Laboratory",
    "specialty_key": "pathology",
    "has_equipment": "False",
    "has_capability": "False",
    "has_procedure": "False",
    "reason": "Pathology requires laboratory facilities",
    "severity": "MEDIUM",
    "flag_type": "MEDICAL_INCONSISTENCY"
  },
  {
    "pk_unique_id": "399",
    "facility_name": "Kumasi Children Hospital",
    "facility_type": "hospital",
    "region": "Unknown",
    "city": "Kumasi",
    "claimed_specialty": "Pediatrics",
    "specialty_key": "pediatrics",
    "has_equipment": "False",
    "has_capability": "False",
    "has_procedure": "False",
    "reason": "Pediatrics requires child-specific care facilities",
    "severity": "MEDIUM",
    "flag_type": "MEDICAL_INCONSISTENCY"
  },
  {
    "pk_unique_id": "96",
    "facility_name": "Awuss Health",
    "facility_type": "nan",
    "region": "Unknown",
    "city": "Accra",
    "claimed_specialty": "Infectious Diseases (incl. TB)",
    "specialty_key": "infectiousDiseases",
    "has_equipment": "False",
    "has_capability": "True",
    "has_procedure": "False",
    "reason": "Infectious disease care requires lab/testing or isolation facilities",
    "severity": "HIGH",
    "flag_type": "MEDICAL_INCONSISTENCY"
  },
  {
    "pk_unique_id": "88",
    "facility_name": "Asokore RCH",
    "facility_type": "hospital",
    "region": "Unknown",
    "city": "Koforidua",
    "claimed_specialty": "Pediatrics",
    "specialty_key": "pediatrics",
    "has_equipment": "False",
    "has_capability": "True",
    "has_procedure": "False",
    "reason": "Pediatrics requires child-specific care facilities",
    "severity": "HIGH",
    "flag_type": "MEDICAL_INCONSISTENCY"
  },
  {
    "pk_unique_id": "796",
    "facility_name": "Zebilla District Hospital",
    "facility_type": "nan",
    "region": "Unknown",
    "city": "Lamboya",
    "claimed_specialty": "Gynecology & Obstetrics",
    "specialty_key": "gynecologyAndObstetrics",
    "has_equipment": "False",
    "has_capability": "True",
    "has_procedure": "False",
    "reason": "OB/GYN requires maternity/delivery facilities",
    "severity": "HIGH",
    "flag_type": "MEDICAL_INCONSISTENCY"
  },
  {
    "pk_unique_id": "723",
    "facility_name": "Tema Polyclinic",
    "facility_type": "nan",
    "region": "Unknown",
    "city": "Tema",
    "claimed_specialty": "Infectious Diseases (incl. TB)",
    "specialty_key": "infectiousDiseases",
    "has_equipment": "False",
    "has_capability": "True",
    "has_procedure": "False",
    "reason": "Infectious disease care requires lab/testing or isolation facilities",
    "severity": "HIGH",
    "flag_type": "MEDICAL_INCONSISTENCY"
  },
  {
    "pk_unique_id": "103",
    "facility_name": "BAMCEC (Bishop Ackon Memorial Christian Eye Centre)",
    "facility_type": "nan",
    "region": "Unknown",
    "city": "Cape Coast",
    "claimed_specialty": "Ophthalmology",
    "specialty_key": "ophthalmology",
    "has_equipment": "False",
    "has_capability": "False",
    "has_procedure": "False",
    "reason": "Ophthalmology requires eye examination equipment",
    "severity": "MEDIUM",
    "flag_type": "MEDICAL_INCONSISTENCY"
  }
]